{
  "gitSyncId": "680277a22638894e86dc32cf_91465d21-2bac-42c3-a901-4cd8f4e8e90b",
  "id": "Login_Auth_UI.setDefaultTab",
  "pluginId": "js-plugin",
  "pluginType": "JS",
  "unpublishedAction": {
    "actionConfiguration": {
      "encodeParamsToggle": true,
      "jsArguments": [
        {
          "name": "newTab"
        }
      ],
      "paginationType": "NONE",
      "timeoutInMillisecond": 10000
    },
    "collectionId": "Login_Auth_UI",
    "confirmBeforeExecute": false,
    "datasource": {
      "isAutoGenerated": false,
      "name": "UNUSED_DATASOURCE",
      "pluginId": "js-plugin"
    },
    "dynamicBindingPathList": [
      {
        "key": "body"
      }
    ],
    "fullyQualifiedName": "Auth_UI.setDefaultTab",
    "name": "setDefaultTab",
    "pageId": "Login",
    "runBehaviour": "MANUAL",
    "userSetOnLoad": true
  }
}