{
  "gitSyncId": "680277a22638894e86dc32cf_20029771-dca2-4b60-b022-376708197d70",
  "id": "KPI Visualizer_KPIToGraphConverter.FormatGraphData",
  "pluginId": "js-plugin",
  "pluginType": "JS",
  "unpublishedAction": {
    "actionConfiguration": {
      "encodeParamsToggle": true,
      "jsArguments": [
        {
          "name": "rawData"
        },
        {
          "name": "groupBy"
        },
        {
          "name": "graphType"
        },
        {
          "name": "fusionChartTypeParam",
          "value": "mscolumn3d"
        }
      ],
      "paginationType": "NONE",
      "timeoutInMillisecond": 10000
    },
    "collectionId": "KPI Visualizer_KPIToGraphConverter",
    "confirmBeforeExecute": false,
    "datasource": {
      "isAutoGenerated": false,
      "name": "UNUSED_DATASOURCE",
      "pluginId": "js-plugin"
    },
    "dynamicBindingPathList": [
      {
        "key": "body"
      }
    ],
    "fullyQualifiedName": "KPIToGraphConverter.FormatGraphData",
    "name": "FormatGraphData",
    "pageId": "KPI Visualizer",
    "runBehaviour": "MANUAL",
    "userSetOnLoad": false
  }
}